imessagefilter/LICENSE
imessagefilter/__init__.py
imessagefilter/msgfilter.c
imessagefilter/msgfilter.dll
imessagefilter/test.py
imessagefilter-0.1.3.dist-info/DESCRIPTION.rst
imessagefilter-0.1.3.dist-info/METADATA
imessagefilter-0.1.3.dist-info/RECORD
imessagefilter-0.1.3.dist-info/WHEEL
imessagefilter-0.1.3.dist-info/metadata.json
imessagefilter-0.1.3.dist-info/top_level.txt
