Metadata-Version: 2.0
Name: imessagefilter
Version: 0.1.3
Summary: A python package implements interface IMessageFilter for COM
Home-page: https://github.com/jondy/imessagefilter
Author: Jondy Zhao
Author-email: jondy.zhao@gmail.com
License: UNKNOWN
Keywords: COM IMessageFilter
Platform: Windows
Classifier: Development Status :: 3 - Alpha
Classifier: Intended Audience :: Developers
Classifier: License :: OSI Approved :: MIT License
Classifier: Operating System :: Microsoft :: Windows
Classifier: Programming Language :: Python :: 2
Classifier: Programming Language :: Python :: 3
